adafruit_circuitplayground/__init__.py
adafruit_circuitplayground/bluefruit.py
adafruit_circuitplayground/circuit_playground_base.py
adafruit_circuitplayground/express.py
adafruit_circuitpython_circuitplayground-5.3.10.dist-info/licenses/LICENSE
adafruit_circuitpython_circuitplayground-5.3.10.dist-info/METADATA
adafruit_circuitpython_circuitplayground-5.3.10.dist-info/WHEEL
adafruit_circuitpython_circuitplayground-5.3.10.dist-info/top_level.txt
adafruit_circuitpython_circuitplayground-5.3.10.dist-info/RECORD
