Metadata-Version: 2.4
Name: adafruit-circuitpython-circuitplayground
Version: 5.3.10
Summary: CircuitPython library for Circuit Playground Express
Author-email: Adafruit Industries <circuitpython@adafruit.com>
License: MIT
Project-URL: Homepage, https://github.com/adafruit/Adafruit_CircuitPython_CircuitPlayground
Keywords: adafruit,circuitplayground,circuit,playground,microcontrollerbluetooth,bluefruit,BLE,hardware,micropython,circuitpython
Classifier: Intended Audience :: Developers
Classifier: Topic :: Software Development :: Libraries
Classifier: Topic :: Software Development :: Embedded Systems
Classifier: Topic :: System :: Hardware
Classifier: License :: OSI Approved :: MIT License
Classifier: Programming Language :: Python :: 3
License-File: LICENSE
Requires-Dist: adafruit-circuitpython-lis3dh
Requires-Dist: adafruit-circuitpython-neopixel
Requires-Dist: adafruit-circuitpython-thermistor
Requires-Dist: typing-extensions
Provides-Extra: optional
Dynamic: license-file
